HSTools-0.0.3.data/scripts/hs
hstools/__init__.py
hstools/auth.py
hstools/compat.py
hstools/hydroshare.py
hstools/log.py
hstools/progress.py
hstools/resource.py
hstools/threads.py
hstools/utilities.py
hstools/funcs/__init__.py
hstools/funcs/add.py
hstools/funcs/content.py
hstools/funcs/create.py
hstools/funcs/delete.py
hstools/funcs/describe.py
hstools/funcs/get.py
hstools/funcs/init.py
hstools/funcs/ls.py
hstools/funcs/move.py
test/__init__.py
test/test_add.py
test/test_auth.py
test/test_create.py
test/test_download.py
HSTools-0.0.3.dist-info/LICENSE
HSTools-0.0.3.dist-info/METADATA
HSTools-0.0.3.dist-info/WHEEL
HSTools-0.0.3.dist-info/top_level.txt
HSTools-0.0.3.dist-info/RECORD
