Metadata-Version: 2.1
Name: HSTools
Version: 0.0.3
Summary: A humble collection of HydroShare tools written in Python
Home-page: https://github.com/castronova/hstools
Author: Anthony M. Castronova
Author-email: acastronova@cuahsi.org
License: UNKNOWN
Platform: UNKNOWN
Classifier: Programming Language :: Python :: 3
Classifier: License :: OSI Approved :: GNU General Public License v3 (GPLv3)
Classifier: Operating System :: OS Independent
Classifier: Natural Language :: English
Classifier: Topic :: Scientific/Engineering :: Hydrology
Requires-Python: >=3.6
Requires-Dist: certifi (>=2019.9.11)
Requires-Dist: chardet (<4,>=3.0.4)
Requires-Dist: hs-restclient (<2,>=1.3)
Requires-Dist: idna (<3,>=2.8)
Requires-Dist: oauthlib (<4,>=3)
Requires-Dist: requests (<3,>=2.22.0)
Requires-Dist: requests-oauthlib (<2,>=1.2.0)
Requires-Dist: requests-toolbelt (<0.10,>=0.9.1)
Requires-Dist: urllib3 (<1.25.9,>=1.25.4)
Requires-Dist: PyYAML (<6,>=5.3)
